kl_pbx/__init__.py
kl_pbx/pbx.py
kl_pbx/version.py
kl_pbx-0.0.4.dist-info/LICENSE
kl_pbx-0.0.4.dist-info/METADATA
kl_pbx-0.0.4.dist-info/WHEEL
kl_pbx-0.0.4.dist-info/top_level.txt
kl_pbx-0.0.4.dist-info/RECORD
