Metadata-Version: 2.1
Name: kl-pbx
Version: 0.0.4
Summary: pbx_tool
Home-page: 
Author: yuxin.zhang
Author-email: whyzi@qq.com
License: MIT
Classifier: License :: OSI Approved :: MIT License
Classifier: Programming Language :: Python
Classifier: Programming Language :: Python :: 3
Classifier: Programming Language :: Python :: 3.6
Classifier: Programming Language :: Python :: Implementation :: CPython
Classifier: Programming Language :: Python :: Implementation :: PyPy
Requires-Python: >=3.6
License-File: LICENSE
Requires-Dist: openstep-parser ==1.5.3
